gmailnudge/__init__.py
gmailnudge/gmailnudge.py
gmailnudge/deployment_files/creds_SMTP
gmailnudge/deployment_files/gmailnudge.cfg
gmailnudge/deployment_files/gmailnudge.service
gmailnudge-2.1.3.dist-info/licenses/LICENSE.txt
gmailnudge-2.1.3.dist-info/METADATA
gmailnudge-2.1.3.dist-info/WHEEL
gmailnudge-2.1.3.dist-info/entry_points.txt
gmailnudge-2.1.3.dist-info/top_level.txt
gmailnudge-2.1.3.dist-info/RECORD
