Metadata-Version: 2.4
Name: gmailnudge
Version: 2.1.3
Summary: Nudge GMail so that it will frequently fetch new emails from another service
Author-email: Chris Nelson <github@cjnaz.com>
License-Expression: MIT
Project-URL: repository, https://github.com/cjnaz/gmailnudge
Keywords: cjnaz,gmail,email
Classifier: Programming Language :: Python :: 3
Classifier: Topic :: Communications :: Email
Requires-Python: >=3.9
License-File: LICENSE.txt
Requires-Dist: cjnfuncs>=3.0.1
Dynamic: license-file
